[
  {"city":{"id":"pouet","name":"Yzeure","country":"FR","country_3366-1":250,"coord":{"lon":"3.354009","lat":"46.565097"}},"cnt":3,"list":[{"dt":1411560000,"main":{"temp":"18","temp_min":"13","temp_max":"15"},"weather":{"description":"belles éclaircies","icon":"2_a"},"clouds":{},"wind":{"speed":"11","deg":"270"}},{"dt":1411581600,"main":{"temp":"11","temp_min":"9","temp_max":"13"},"weather":{"description":"belles éclaircies","icon":"2_a"},"clouds":{},"wind":{"speed":"7","deg":"270"}},{"dt":1411596000,"main":{"temp":"10","temp_min":"9","temp_max":"9"},"weather":{"description":"très nuageux","icon":"3_a"},"clouds":{},"wind":{"speed":"11","deg":"315"}}]},

  {"city":{"id":"pouet","name":"Nice","country":"FR","country_3366-1":250,"coord":{"lon":"7.267120","lat":"43.701513"}},"cnt":3,"list":[{"dt":1411560000,"main":{"temp":"22","temp_min":"20","temp_max":"22"},"weather":{"description":"pluies éparses","icon":"9_c"},"clouds":{},"wind":{"speed":"11","deg":"90"}},{"dt":1411581600,"main":{"temp":"19","temp_min":"18","temp_max":"20"},"weather":{"description":"très nuageux","icon":"3_a"},"clouds":{},"wind":{"speed":"4","deg":"335"}},{"dt":1411596000,"main":{"temp":"17","temp_min":"16","temp_max":"18"},"weather":{"description":"nuit claire","icon":"0_b"},"clouds":{},"wind":{"speed":"14","deg":"45"}}]},

  {"city":{"id":"pouet","name":"Charleville-Mézières","country":"FR","country_3366-1":250,"coord":{"lon":"4.718810","lat":"49.771159"}},"cnt":3,"list":[{"dt":1411560000,"main":{"temp":"16","temp_min":"13","temp_max":"16"},"weather":{"description":"rares averses","icon":"9_c"},"clouds":{},"wind":{"speed":"14","deg":"245"}},{"dt":1411581600,"main":{"temp":"10","temp_min":"8","temp_max":"13"},"weather":{"description":"rares averses","icon":"9_a"},"clouds":{},"wind":{"speed":"11","deg":"315"}},{"dt":1411596000,"main":{"temp":"8","temp_min":"7","temp_max":"8"},"weather":{"description":"bancs de brouillard","icon":"4_b"},"clouds":{},"wind":{"speed":"7","deg":"315"}}]},

  {"city":{"id":"pouet","name":"Troyes","country":"FR","country_3366-1":250,"coord":{"lon":"4.077630","lat":"48.298132"}},"cnt":3,"list":[{"dt":1411560000,"main":{"temp":"18","temp_min":"15","temp_max":"17"},"weather":{"description":"belles éclaircies","icon":"2_a"},"clouds":{},"wind":{"speed":"14","deg":"290"}},{"dt":1411581600,"main":{"temp":"11","temp_min":"10","temp_max":"15"},"weather":{"description":"rares averses","icon":"9_a"},"clouds":{},"wind":{"speed":"11","deg":"245"}},{"dt":1411596000,"main":{"temp":"8","temp_min":"8","temp_max":"10"},"weather":{"description":"brume","icon":"4_b"},"clouds":{},"wind":{"speed":"7","deg":"290"}}]},

  {"city":{"id":"pouet","name":"Villeneuve","country":"FR","country_3366-1":250,"coord":{"lon":"2.031561","lat":"44.437206"}},"cnt":3,"list":[{"dt":1411560000,"main":{"temp":"19","temp_min":"16","temp_max":"19"},"weather":{"description":"eclaircies","icon":"2_a"},"clouds":{},"wind":{"speed":"14","deg":"270"}},{"dt":1411581600,"main":{"temp":"13","temp_min":"12","temp_max":"16"},"weather":{"description":"belles éclaircies","icon":"2_a"},"clouds":{},"wind":{"speed":"11","deg":"290"}},{"dt":1411596000,"main":{"temp":"9","temp_min":"8","temp_max":"12"},"weather":{"description":"nuit claire","icon":"0_b"},"clouds":{},"wind":{"speed":"4","deg":"200"}}]},

  {"city":{"id":"pouet","name":"Marseille","country":"FR","country_3366-1":250,"coord":{"lon":"5.375945","lat":"43.296199"}},"cnt":3,"list":[{"dt":1411560000,"main":{"temp":"20","temp_min":"19","temp_max":"20"},"weather":{"description":"averses orageuses","icon":"12_c"},"clouds":{},"wind":{"speed":"11","deg":"200"}},{"dt":1411581600,"main":{"temp":"18","temp_min":"17","temp_max":"19"},"weather":{"description":"eclaircies","icon":"2_a"},"clouds":{},"wind":{"speed":"7","deg":"315"}},{"dt":1411596000,"main":{"temp":"16","temp_min":"15","temp_max":"17"},"weather":{"description":"nuit claire","icon":"0_b"},"clouds":{},"wind":{"speed":"22","deg":"335"}}]},

  {"city":{"id":"pouet","name":"Saintes","country":"FR","country_3366-1":250,"coord":{"lon":"-0.635019","lat":"45.744861"}},"cnt":3,"list":[{"dt":1411560000,"main":{"temp":"18","temp_min":"17","temp_max":"19"},"weather":{"description":"belles éclaircies","icon":"2_a"},"clouds":{},"wind":{"speed":"14","deg":"315"}},{"dt":1411581600,"main":{"temp":"14","temp_min":"12","temp_max":"17"},"weather":{"description":"belles éclaircies","icon":"2_a"},"clouds":{},"wind":{"speed":"14","deg":"290"}},{"dt":1411596000,"main":{"temp":"11","temp_min":"11","temp_max":"12"},"weather":{"description":"pluies éparses","icon":"9_c"},"clouds":{},"wind":{"speed":"0","deg":"-1"}}]},

  {"city":{"id":"pouet","name":"Tulle","country":"FR","country_3366-1":250,"coord":{"lon":"1.772220","lat":"45.265482"}},"cnt":3,"list":[{"dt":1411560000,"main":{"temp":"19","temp_min":"15","temp_max":"18"},"weather":{"description":"eclaircies","icon":"2_a"},"clouds":{},"wind":{"speed":"7","deg":"290"}},{"dt":1411581600,"main":{"temp":"12","temp_min":"10","temp_max":"15"},"weather":{"description":"belles éclaircies","icon":"2_a"},"clouds":{},"wind":{"speed":"7","deg":"335"}},{"dt":1411596000,"main":{"temp":"9","temp_min":"8","temp_max":"10"},"weather":{"description":"eclaircies","icon":"2_b"},"clouds":{},"wind":{"speed":"0","deg":"-1"}}]},

  {"city":{"id":"pouet","name":"Ajaccio","country":"FR","country_3366-1":250,"coord":{"lon":"8.735601","lat":"41.925112"}},"cnt":3,"list":[{"dt":1411560000,"main":{"temp":"25","temp_min":"20","temp_max":"21"},"weather":{"description":"rares averses","icon":"9_a"},"clouds":{},"wind":{"speed":"7","deg":"290"}},{"dt":1411581600,"main":{"temp":"17","temp_min":"16","temp_max":"20"},"weather":{"description":"eclaircies","icon":"2_a"},"clouds":{},"wind":{"speed":"7","deg":"155"}},{"dt":1411596000,"main":{"temp":"16","temp_min":"16","temp_max":"16"},"weather":{"description":"rares averses","icon":"9_b"},"clouds":{},"wind":{"speed":"7","deg":"45"}}]},

  {"city":{"id":"pouet","name":"Bastia","country":"FR","country_3366-1":250,"coord":{"lon":"9.449454","lat":"42.699383"}},"cnt":3,"list":[{"dt":1411560000,"main":{"temp":"23","temp_min":"19","temp_max":"25"},"weather":{"description":"eclaircies","icon":"2_a"},"clouds":{},"wind":{"speed":"11","deg":"20"}},{"dt":1411581600,"main":{"temp":"17","temp_min":"17","temp_max":"19"},"weather":{"description":"eclaircies","icon":"2_a"},"clouds":{},"wind":{"speed":"11","deg":"155"}},{"dt":1411596000,"main":{"temp":"16","temp_min":"17","temp_max":"17"},"weather":{"description":"rares averses","icon":"9_b"},"clouds":{},"wind":{"speed":"7","deg":"20"}}]},

  {"city":{"id":"pouet","name":"Dijon","country":"FR","country_3366-1":250,"coord":{"lon":"5.041065","lat":"47.322479"}},"cnt":3,"list":[{"dt":1411560000,"main":{"temp":"18","temp_min":"15","temp_max":"16"},"weather":{"description":"eclaircies","icon":"2_a"},"clouds":{},"wind":{"speed":"11","deg":"270"}},{"dt":1411581600,"main":{"temp":"12","temp_min":"10","temp_max":"15"},"weather":{"description":"belles éclaircies","icon":"2_a"},"clouds":{},"wind":{"speed":"7","deg":"290"}},{"dt":1411596000,"main":{"temp":"10","temp_min":"10","temp_max":"10"},"weather":{"description":"eclaircies","icon":"2_b"},"clouds":{},"wind":{"speed":"7","deg":"335"}}]},

  {"city":{"id":"pouet","name":"Valence","country":"FR","country_3366-1":250,"coord":{"lon":"4.889825","lat":"44.932533"}},"cnt":3,"list":[{"dt":1411560000,"main":{"temp":"16","temp_min":"15","temp_max":"17"},"weather":{"description":"pluie","icon":"10_c"},"clouds":{},"wind":{"speed":"7","deg":"360"}},{"dt":1411581600,"main":{"temp":"14","temp_min":"13","temp_max":"15"},"weather":{"description":"eclaircies","icon":"2_a"},"clouds":{},"wind":{"speed":"11","deg":"20"}},{"dt":1411596000,"main":{"temp":"11","temp_min":"10","temp_max":"13"},"weather":{"description":"belles éclaircies","icon":"2_b"},"clouds":{},"wind":{"speed":"18","deg":"360"}}]},

  {"city":{"id":"pouet","name":"Quimper","country":"FR","country_3366-1":250,"coord":{"lon":"-4.098931","lat":"47.995753"}},"cnt":3,"list":[{"dt":1411560000,"main":{"temp":"18","temp_min":"16","temp_max":"19"},"weather":{"description":"eclaircies","icon":"2_a"},"clouds":{},"wind":{"speed":"22","deg":"315"}},{"dt":1411581600,"main":{"temp":"13","temp_min":"12","temp_max":"16"},"weather":{"description":"eclaircies","icon":"2_a"},"clouds":{},"wind":{"speed":"14","deg":"335"}},{"dt":1411596000,"main":{"temp":"11","temp_min":"9","temp_max":"12"},"weather":{"description":"bancs de brouillard","icon":"4_b"},"clouds":{},"wind":{"speed":"7","deg":"45"}}]},

  {"city":{"id":"pouet","name":"Vézénobres","country":"FR","country_3366-1":250,"coord":{"lon":"4.135599","lat":"44.052331"}},"cnt":3,"list":[{"dt":1411560000,"main":{"temp":"18","temp_min":"15","temp_max":"15"},"weather":{"description":"pluies éparses","icon":"9_a"},"clouds":{},"wind":{"speed":"7","deg":"20"}},{"dt":1411581600,"main":{"temp":"14","temp_min":"13","temp_max":"15"},"weather":{"description":"eclaircies","icon":"2_a"},"clouds":{},"wind":{"speed":"4","deg":"360"}},{"dt":1411596000,"main":{"temp":"13","temp_min":"11","temp_max":"13"},"weather":{"description":"nuit claire","icon":"0_b"},"clouds":{},"wind":{"speed":"14","deg":"360"}}]},

  {"city":{"id":"pouet","name":"Toulouse","country":"FR","country_3366-1":250,"coord":{"lon":"1.441079","lat":"43.604098"}},"cnt":3,"list":[{"dt":1411560000,"main":{"temp":"21","temp_min":"19","temp_max":"20"},"weather":{"description":"eclaircies","icon":"2_a"},"clouds":{},"wind":{"speed":"22","deg":"290"}},{"dt":1411581600,"main":{"temp":"16","temp_min":"14","temp_max":"19"},"weather":{"description":"belles éclaircies","icon":"2_a"},"clouds":{},"wind":{"speed":"14","deg":"290"}},{"dt":1411596000,"main":{"temp":"12","temp_min":"11","temp_max":"14"},"weather":{"description":"nuit claire","icon":"0_b"},"clouds":{},"wind":{"speed":"11","deg":"270"}}]},

  {"city":{"id":"pouet","name":"Bordeaux","country":"FR","country_3366-1":250,"coord":{"lon":"-0.580433","lat":"44.837098"}},"cnt":3,"list":[{"dt":1411560000,"main":{"temp":"20","temp_min":"17","temp_max":"20"},"weather":{"description":"belles éclaircies","icon":"2_a"},"clouds":{},"wind":{"speed":"14","deg":"315"}},{"dt":1411581600,"main":{"temp":"14","temp_min":"12","temp_max":"17"},"weather":{"description":"belles éclaircies","icon":"2_a"},"clouds":{},"wind":{"speed":"7","deg":"270"}},{"dt":1411596000,"main":{"temp":"11","temp_min":"11","temp_max":"12"},"weather":{"description":"eclaircies","icon":"2_b"},"clouds":{},"wind":{"speed":"4","deg":"180"}}]},

  {"city":{"id":"pouet","name":"Rennes","country":"FR","country_3366-1":250,"coord":{"lon":"-1.681487","lat":"48.113628"}},"cnt":3,"list":[{"dt":1411560000,"main":{"temp":"19","temp_min":"17","temp_max":"19"},"weather":{"description":"eclaircies","icon":"2_a"},"clouds":{},"wind":{"speed":"14","deg":"315"}},{"dt":1411581600,"main":{"temp":"14","temp_min":"11","temp_max":"17"},"weather":{"description":"eclaircies","icon":"2_a"},"clouds":{},"wind":{"speed":"11","deg":"290"}},{"dt":1411596000,"main":{"temp":"10","temp_min":"8","temp_max":"11"},"weather":{"description":"bancs de brouillard","icon":"4_b"},"clouds":{},"wind":{"speed":"7","deg":"225"}}]},

  {"city":{"id":"pouet","name":"Nantes","country":"FR","country_3366-1":250,"coord":{"lon":"-1.554608","lat":"47.216500"}},"cnt":3,"list":[{"dt":1411560000,"main":{"temp":"21","temp_min":"18","temp_max":"19"},"weather":{"description":"belles éclaircies","icon":"2_a"},"clouds":{},"wind":{"speed":"11","deg":"315"}},{"dt":1411581600,"main":{"temp":"15","temp_min":"13","temp_max":"18"},"weather":{"description":"rares averses","icon":"9_a"},"clouds":{},"wind":{"speed":"11","deg":"360"}},{"dt":1411596000,"main":{"temp":"11","temp_min":"10","temp_max":"13"},"weather":{"description":"brume","icon":"4_b"},"clouds":{},"wind":{"speed":"4","deg":"335"}}]},

  {"city":{"id":"pouet","name":"Orléans","country":"FR","country_3366-1":250,"coord":{"lon":"1.903198","lat":"47.901941"}},"cnt":3,"list":[{"dt":1411560000,"main":{"temp":"18","temp_min":"15","temp_max":"18"},"weather":{"description":"belles éclaircies","icon":"2_a"},"clouds":{},"wind":{"speed":"11","deg":"290"}},{"dt":1411581600,"main":{"temp":"12","temp_min":"10","temp_max":"15"},"weather":{"description":"rares averses","icon":"9_a"},"clouds":{},"wind":{"speed":"14","deg":"290"}},{"dt":1411596000,"main":{"temp":"9","temp_min":"8","temp_max":"10"},"weather":{"description":"bancs de brouillard","icon":"4_b"},"clouds":{},"wind":{"speed":"4","deg":"270"}}]},

  {"city":{"id":"pouet","name":"Saint-Lô","country":"FR","country_3366-1":250,"coord":{"lon":"-1.092068","lat":"49.113968"}},"cnt":3,"list":[{"dt":1411560000,"main":{"temp":"17","temp_min":"15","temp_max":"17"},"weather":{"description":"rares averses","icon":"9_a"},"clouds":{},"wind":{"speed":"11","deg":"270"}},{"dt":1411581600,"main":{"temp":"10","temp_min":"9","temp_max":"15"},"weather":{"description":"belles éclaircies","icon":"2_a"},"clouds":{},"wind":{"speed":"7","deg":"290"}},{"dt":1411596000,"main":{"temp":"8","temp_min":"4","temp_max":"9"},"weather":{"description":"brume","icon":"4_b"},"clouds":{},"wind":{"speed":"7","deg":"180"}}]},

  {"city":{"id":"pouet","name":"Vigneulles-lès-Hattonchâtel","country":"FR","country_3366-1":250,"coord":{"lon":"5.702951","lat":"48.980861"}},"cnt":3,"list":[{"dt":1411560000,"main":{"temp":"17","temp_min":"13","temp_max":"16"},"weather":{"description":"belles éclaircies","icon":"2_a"},"clouds":{},"wind":{"speed":"14","deg":"270"}},{"dt":1411581600,"main":{"temp":"11","temp_min":"11","temp_max":"13"},"weather":{"description":"rares averses","icon":"9_a"},"clouds":{},"wind":{"speed":"11","deg":"245"}},{"dt":1411596000,"main":{"temp":"10","temp_min":"9","temp_max":"11"},"weather":{"description":"eclaircies","icon":"2_b"},"clouds":{},"wind":{"speed":"7","deg":"270"}}]},{"city":{"id":"pouet","name":"Lille","country":"FR","country_3366-1":250,"coord":{"lon":"3.057161","lat":"50.631573"}},"cnt":3,"list":[{"dt":1411560000,"main":{"temp":"16","temp_min":"14","temp_max":"14"},"weather":{"description":"averses orageuses","icon":"12_c"},"clouds":{},"wind":{"speed":"11","deg":"290"}},{"dt":1411581600,"main":{"temp":"12","temp_min":"11","temp_max":"14"},"weather":{"description":"averses","icon":"10_c"},"clouds":{},"wind":{"speed":"11","deg":"270"}},{"dt":1411596000,"main":{"temp":"10","temp_min":"9","temp_max":"11"},"weather":{"description":"brume","icon":"4_b"},"clouds":{},"wind":{"speed":"7","deg":"225"}}]},{"city":{"id":"pouet","name":"Saint-Quentin-de-Blavou","country":"FR","country_3366-1":250,"coord":{"lon":"0.416581","lat":"48.469799"}},"cnt":3,"list":[{"dt":1411560000,"main":{"temp":"16","temp_min":"14","temp_max":"17"},"weather":{"description":"rares averses","icon":"9_a"},"clouds":{},"wind":{"speed":"18","deg":"290"}},{"dt":1411581600,"main":{"temp":"11","temp_min":"10","temp_max":"14"},"weather":{"description":"rares averses","icon":"9_a"},"clouds":{},"wind":{"speed":"7","deg":"290"}},{"dt":1411596000,"main":{"temp":"9","temp_min":"9","temp_max":"10"},"weather":{"description":"bancs de brouillard","icon":"4_b"},"clouds":{},"wind":{"speed":"0","deg":"-1"}}]},{"city":{"id":"pouet","name":"Ustaritz","country":"FR","country_3366-1":250,"coord":{"lon":"-1.457041","lat":"43.399042"}},"cnt":3,"list":[{"dt":1411560000,"main":{"temp":"20","temp_min":"18","temp_max":"20"},"weather":{"description":"eclaircies","icon":"2_a"},"clouds":{},"wind":{"speed":"14","deg":"315"}},{"dt":1411581600,"main":{"temp":"16","temp_min":"14","temp_max":"18"},"weather":{"description":"belles éclaircies","icon":"2_a"},"clouds":{},"wind":{"speed":"7","deg":"335"}},{"dt":1411596000,"main":{"temp":"13","temp_min":"12","temp_max":"14"},"weather":{"description":"eclaircies","icon":"2_b"},"clouds":{},"wind":{"speed":"4","deg":"155"}}]},{"city":{"id":"pouet","name":"Perpignan","country":"FR","country_3366-1":250,"coord":{"lon":"2.894200","lat":"42.697131"}},"cnt":3,"list":[{"dt":1411560000,"main":{"temp":"23","temp_min":"21","temp_max":"24"},"weather":{"description":"eclaircies","icon":"2_a"},"clouds":{},"wind":{"speed":"18","deg":"315"}},{"dt":1411581600,"main":{"temp":"19","temp_min":"18","temp_max":"21"},"weather":{"description":"belles éclaircies","icon":"2_a"},"clouds":{},"wind":{"speed":"29","deg":"315"}},{"dt":1411596000,"main":{"temp":"16","temp_min":"15","temp_max":"18"},"weather":{"description":"nuit claire","icon":"0_b"},"clouds":{},"wind":{"speed":"29","deg":"315"}}]},{"city":{"id":"pouet","name":"Strasbourg","country":"FR","country_3366-1":250,"coord":{"lon":"7.746694","lat":"48.583085"}},"cnt":3,"list":[{"dt":1411560000,"main":{"temp":"18","temp_min":"13","temp_max":"18"},"weather":{"description":"eclaircies","icon":"2_a"},"clouds":{},"wind":{"speed":"14","deg":"200"}},{"dt":1411581600,"main":{"temp":"11","temp_min":"11","temp_max":"13"},"weather":{"description":"belles éclaircies","icon":"2_a"},"clouds":{},"wind":{"speed":"7","deg":"200"}},{"dt":1411596000,"main":{"temp":"11","temp_min":"11","temp_max":"11"},"weather":{"description":"brume","icon":"4_b"},"clouds":{},"wind":{"speed":"0","deg":"-1"}}]},{"city":{"id":"pouet","name":"Thann","country":"FR","country_3366-1":250,"coord":{"lon":"7.104005","lat":"47.806301"}},"cnt":3,"list":[{"dt":1411560000,"main":{"temp":"16","temp_min":"13","temp_max":"19"},"weather":{"description":"très nuageux","icon":"3_a"},"clouds":{},"wind":{"speed":"18","deg":"245"}},{"dt":1411581600,"main":{"temp":"12","temp_min":"11","temp_max":"13"},"weather":{"description":"belles éclaircies","icon":"2_a"},"clouds":{},"wind":{"speed":"14","deg":"225"}},{"dt":1411596000,"main":{"temp":"10","temp_min":"10","temp_max":"11"},"weather":{"description":"eclaircies","icon":"2_b"},"clouds":{},"wind":{"speed":"7","deg":"245"}}]},{"city":{"id":"pouet","name":"Lyon","country":"FR","country_3366-1":250,"coord":{"lon":"4.840700","lat":"45.758097"}},"cnt":3,"list":[{"dt":1411560000,"main":{"temp":"17","temp_min":"16","temp_max":"15"},"weather":{"description":"pluies éparses","icon":"9_c"},"clouds":{},"wind":{"speed":"4","deg":"360"}},{"dt":1411581600,"main":{"temp":"14","temp_min":"13","temp_max":"16"},"weather":{"description":"pluies éparses","icon":"9_a"},"clouds":{},"wind":{"speed":"0","deg":"-1"}},{"dt":1411596000,"main":{"temp":"10","temp_min":"11","temp_max":"13"},"weather":{"description":"eclaircies","icon":"2_b"},"clouds":{},"wind":{"speed":"7","deg":"315"}}]},{"city":{"id":"pouet","name":"Évian-les-Bains","country":"FR","country_3366-1":250,"coord":{"lon":"6.589808","lat":"46.400094"}},"cnt":3,"list":[{"dt":1411560000,"main":{"temp":"16","temp_min":"13","temp_max":"16"},"weather":{"description":"eclaircies","icon":"2_a"},"clouds":{},"wind":{"speed":"11","deg":"245"}},{"dt":1411581600,"main":{"temp":"12","temp_min":"12","temp_max":"13"},"weather":{"description":"pluies éparses","icon":"9_c"},"clouds":{},"wind":{"speed":"7","deg":"245"}},{"dt":1411596000,"main":{"temp":"10","temp_min":"10","temp_max":"12"},"weather":{"description":"belles éclaircies","icon":"2_b"},"clouds":{},"wind":{"speed":"7","deg":"315"}}]},

  {"city":{"id":"pouet","name":"Paris","country":"FR","country_3366-1":250,"coord":{"lon":"2.340591","lat":"48.859333"}},"cnt":3,"list":[{"dt":1411560000,"main":{"temp":"18","temp_min":"16","temp_max":"18"},"weather":{"description":"eclaircies","icon":"2_a"},"clouds":{},"wind":{"speed":"18","deg":"270"}},{"dt":1411581600,"main":{"temp":"14","temp_min":"13","temp_max":"16"},"weather":{"description":"belles éclaircies","icon":"2_a"},"clouds":{},"wind":{"speed":"11","deg":"290"}},{"dt":1411596000,"main":{"temp":"12","temp_min":"11","temp_max":"13"},"weather":{"description":"belles éclaircies","icon":"2_b"},"clouds":{},"wind":{"speed":"7","deg":"270"}}]},

  {"city":{"id":"pouet","name":"Yvetot","country":"FR","country_3366-1":250,"coord":{"lon":"0.752315","lat":"49.616213"}},"cnt":3,"list":[{"dt":1411560000,"main":{"temp":"16","temp_min":"14","temp_max":"16"},"weather":{"description":"averses","icon":"10_c"},"clouds":{},"wind":{"speed":"22","deg":"290"}},{"dt":1411581600,"main":{"temp":"12","temp_min":"11","temp_max":"14"},"weather":{"description":"eclaircies","icon":"2_a"},"clouds":{},"wind":{"speed":"11","deg":"335"}},{"dt":1411596000,"main":{"temp":"10","temp_min":"9","temp_max":"11"},"weather":{"description":"brume","icon":"4_b"},"clouds":{},"wind":{"speed":"0","deg":"-1"}}]},

  {"city":{"id":"pouet","name":"Poitiers","country":"FR","country_3366-1":250,"coord":{"lon":"0.334765","lat":"46.580835"}},"cnt":3,"list":[{"dt":1411560000,"main":{"temp":"19","temp_min":"16","temp_max":"17"},"weather":{"description":"belles éclaircies","icon":"2_a"},"clouds":{},"wind":{"speed":"14","deg":"315"}},{"dt":1411581600,"main":{"temp":"13","temp_min":"11","temp_max":"16"},"weather":{"description":"eclaircies","icon":"2_a"},"clouds":{},"wind":{"speed":"7","deg":"225"}},{"dt":1411596000,"main":{"temp":"10","temp_min":"9","temp_max":"11"},"weather":{"description":"brume","icon":"4_b"},"clouds":{},"wind":{"speed":"4","deg":"290"}}]}]